pylhe/__init__.py
pylhe/_version.py
pylhe/_version.pyi
pylhe/awkward.py
pylhe/py.typed
pylhe-1.0.2.dist-info/METADATA
pylhe-1.0.2.dist-info/WHEEL
pylhe-1.0.2.dist-info/licenses/LICENSE
pylhe-1.0.2.dist-info/RECORD
