Metadata-Version: 2.4
Name: pylhe
Version: 1.0.2
Summary: A small package to get structured data out of Les Houches Event files
Project-URL: Homepage, https://github.com/scikit-hep/pylhe
Project-URL: Source Code, https://github.com/scikit-hep/pylhe
Project-URL: Issue Tracker, https://github.com/scikit-hep/pylhe/issues
Project-URL: Releases, https://github.com/scikit-hep/pylhe/releases
Author-email: Lukas Heinrich <lukas.heinrich@cern.ch>, Matthew Feickert <matthew.feickert@cern.ch>, Eduardo Rodrigues <eduardo.rodrigues@cern.ch>, Alexander Puck Neuwirth <a_neuw01@uni-muenster.de>
Maintainer-email: The Scikit-HEP admins <scikit-hep-admins@googlegroups.com>
License: Apache-2.0
License-File: LICENSE
Keywords: lhe,physics
Classifier: Development Status :: 4 - Beta
Classifier: Intended Audience :: Developers
Classifier: Intended Audience :: Science/Research
Classifier: License :: OSI Approved :: Apache Software License
Classifier: Programming Language :: Python :: 3
Classifier: Programming Language :: Python :: 3 :: Only
Classifier: Programming Language :: Python :: 3.9
Classifier: Programming Language :: Python :: 3.10
Classifier: Programming Language :: Python :: 3.11
Classifier: Programming Language :: Python :: 3.12
Classifier: Programming Language :: Python :: 3.13
Classifier: Programming Language :: Python :: 3.14
Classifier: Topic :: Scientific/Engineering
Classifier: Topic :: Scientific/Engineering :: Physics
Requires-Python: >=3.9
Requires-Dist: awkward>=1.2.0
Requires-Dist: graphviz>=0.19
Requires-Dist: particle>=0.16
Requires-Dist: vector>=0.8.1
Provides-Extra: develop
Requires-Dist: mypy>=1.0.0; extra == 'develop'
Requires-Dist: pre-commit; extra == 'develop'
Requires-Dist: pydocstyle; extra == 'develop'
Requires-Dist: pytest-benchmark; extra == 'develop'
Requires-Dist: pytest-cov>=2.5.1; extra == 'develop'
Requires-Dist: pytest>=6.0; extra == 'develop'
Requires-Dist: ruff; extra == 'develop'
Requires-Dist: scikit-hep-testdata>=0.5.5; extra == 'develop'
Requires-Dist: tbump>=6.7.0; extra == 'develop'
Provides-Extra: docs
Requires-Dist: jupyter-sphinx; extra == 'docs'
Requires-Dist: myst-nb; extra == 'docs'
Requires-Dist: myst-parser; extra == 'docs'
Requires-Dist: nbsphinx; extra == 'docs'
Requires-Dist: pandoc; extra == 'docs'
Requires-Dist: sphinx; extra == 'docs'
Requires-Dist: sphinx-autoapi; extra == 'docs'
Requires-Dist: sphinx-autobuild; extra == 'docs'
Requires-Dist: sphinx-copybutton; extra == 'docs'
Requires-Dist: sphinx-math-dollar; extra == 'docs'
Requires-Dist: sphinx-rtd-theme>=0.5.0; extra == 'docs'
Requires-Dist: sphinxcontrib-bibtex; extra == 'docs'
Requires-Dist: toml; extra == 'docs'
Provides-Extra: lint
Requires-Dist: mypy>=1.0.0; extra == 'lint'
Requires-Dist: ruff; extra == 'lint'
Provides-Extra: test
Requires-Dist: pydocstyle; extra == 'test'
Requires-Dist: pytest-benchmark; extra == 'test'
Requires-Dist: pytest-cov>=2.5.1; extra == 'test'
Requires-Dist: pytest>=6.0; extra == 'test'
Requires-Dist: scikit-hep-testdata>=0.5.5; extra == 'test'
